bowbow/__init__.py
bowbow/sum.py
theaikit-1.0.0.dist-info/LICENCE.txt
theaikit-1.0.0.dist-info/METADATA
theaikit-1.0.0.dist-info/WHEEL
theaikit-1.0.0.dist-info/top_level.txt
theaikit-1.0.0.dist-info/RECORD
