Metadata-Version: 2.1
Name: theaikit
Version: 1.0.0
Summary: An AI module
Home-page: https://github.com/anirudhambati/AI-Material.git
Author: Anirudh Ambati
Author-email: anirudhambati@gmail.com
License: MIT
Keywords: example
Platform: UNKNOWN
